{"cameraMode":{"drawMode":0,"name":"Shaded","section":"Shading Mode"},"sceneLighting":true,"audioPlay":false,"sceneViewState":{"m_AlwaysRefresh":true,"showFog":true,"showSkybox":true,"showFlares":true,"showImageEffects":true,"showParticleSystems":true,"showVisualEffectGraphs":true,"m_FxEnabled":true},"in2DMode":false,"pivot":{"x":-19.700000762939454,"y":50.0,"z":20.700000762939454},"rotation":{"x":-0.08689907938241959,"y":0.7797741889953613,"z":-0.6100740432739258,"w":-0.11770305037498474},"size":23.464052200317384,"orthographic":false}